.gitignore
AUTHORS
CHANGES.txt
LICENSE
MANIFEST.in
README.rst
requirements.txt
runtests.py
setup.py
tox.ini
django_hijackemail.egg-info/PKG-INFO
django_hijackemail.egg-info/SOURCES.txt
django_hijackemail.egg-info/dependency_links.txt
django_hijackemail.egg-info/not-zip-safe
django_hijackemail.egg-info/top_level.txt
hijackemail/__init__.py
hijackemail/backends.py
hijackemail/models.py
hijackemail/tests.py