Metadata-Version: 1.1
Name: django-hijackemail
Version: 1.0.0
Summary: Reroute outgoing mail (for use in dev/testing/staging environments)
Home-page: https://github.com/katylava/django-hijackemail
Author: Katy LaVallee
Author-email: katy@firelightweb.com
License: MIT
Platform: UNKNOWN
Classifier: Development Status :: 5 - Production/Stable
Classifier: Framework :: Django
Classifier: Intended Audience :: Developers
Classifier: License :: OSI Approved :: MIT License
Classifier: Operating System :: OS Independent
Classifier: Programming Language :: Python
Classifier: Programming Language :: Python :: 2.7
Classifier: Programming Language :: Python :: 3
Classifier: Topic :: Communications :: Email
Classifier: Topic :: Internet :: WWW/HTTP :: Dynamic Content
Classifier: Topic :: Software Development :: Quality Assurance
